{
    "buses":
    [
        {
        "number": "202",
        "time": "6:50"
    },
    {
        "number": "113",
        "time": "7:00"
    },
    {
        "number": "614",
        "time": "7:20",
        "note": "В Переможне"
    },
    {
        "number": "603",
        "time": "7:30"
    },
    {
        "number": "604 A",
        "time": "7:50"
    },
    {
        "number": "113",
        "time": "8:00"
    },
    {
        "number": "614",
        "time": "8:20",
        "note": "В Тулиголове"
    },
    {
        "number": "118",
        "time": "8:30",
        "note": "Крім неділі"
    },
    {
        "number": "202",
        "time": "8:40"
    },
    {
        "number": "109",
        "time": "9:00"
    },
    {
        "number": "604 Б",
        "time": "9:10"
    },
    {
        "number": "113 A",
        "time": "9:20"
    },
    {
        "number": "603",
        "time": "9:30"
    },
    {
        "number": "604 A",
        "time": "9:40"
    },
    {
        "number": "614",
        "time": "10:00",
        "note": "В Переможне"
    },
    {
        "number": "113",
        "time": "10:10"
    },
    {
        "number": "604 Б",
        "time": "10:40"
    },
    {
        "number": "118",
        "time": "10:50",
        "note": "На Дмитре"
    },
    {
        "number": "132",
        "time": "11:00"
    },
    {
        "number": "603",
        "time": "11:30"
    },
    {
        "number": "109",
        "time": "11:40"
    },
    {
        "number": "614",
        "time": "12:00",
        "note": "В Переможне"
    },
    {
        "number": "604 Б",
        "time": "12:20"
    },
    {
        "number": "118",
        "time": "12:30",
        "note": "В Черкаси"
    },
    { 
        "number": "113 A",
        "time": "12:40" 
    },
    { 
        "number": "614",
        "time": "13:20",
        "note": "В Переможне" 
    },
    { 
        "number": "603",
        "time": "13:30" 
    },
    { 
        "number": "604 A",
        "time": "13:40" 
    },
    { 
        "number": "202",
        "time": "14:00" 
    },
    { 
        "number": "113",
        "time": "14:10" 
    },
    { 
        "number": "604 Б",
        "time": "14:20" 
    },
    { 
        "number": "614",
        "time": "14:40",
        "note": "В Тулиголове" 
    },
    { 
        "number": "118",
        "time": "14:50",
        "note": "На Дмитре" 
    },
    { 
        "number": "202",
        "time": "15:10" 
    },
    { 
        "number": "603",
        "time": "15:20" 
    },
    { 
        "number": "604 A",
        "time": "15:40" 
    },
    { 
        "number": "614",
        "time": "16:00",
        "note": "В Переможне" 
    },
    { 
        "number": "113 A",
        "time": "16:10" 
    },
    { 
        "number": "109",
        "time": "16:30" 
    },
    { 
        "number": "118",
        "time": "16:40",
        "note": "В Черкаси" 
    },
    { 
        "number": "113",
        "time": "17:10" 
    },
    { 
        "number": "603",
        "time": "17:30" 
    },
    { 
        "number": "604 A",
        "time": "17:40" 
    },
    { 
        "number": "132",
        "time": "17:50" 
    },
    { 
        "number": "614",
        "time": "18:00",
        "note": "В Тулиголове" 
    },
    { 
        "number": "113",
        "time": "18:10" 
    },
    { 
        "number": "604 Б",
        "time": "18:20" 
    },
    { 
        "number": "202",
        "time": "18:30" 
    },
    { 
        "number": "614",
        "time": "18:40",
        "note": "В Переможне" 
    },
    { 
        "number": "603",
        "time": "18:50" 
    },
    { 
        "number": "604 Б",
        "time": "19:00" 
    },
    { 
        "number": "109",
        "time": "19:10" 
    },
    { 
        "number": "113 A",
        "time": "19:20" 
    },
    { 
        "number": "603",
        "time": "19:30" 
    },
    { 
        "number": "604 A",
        "time": "19:40" 
    },
    { 
        "number": "118",
        "time": "19:50",
        "note": "На Дмитре" 
    },
    { 
        "number": "614",
        "time": "20:00",
        "note": "В Комарно" 
    },
    { 
        "number": "113",
        "time": "20:10" 
    },
    { 
        "number": "118",
        "time": "20:30",
        "note": "В Черкаси" 
    },
    { 
        "number": "132",
        "time": "21:00" 
    }
    ]
}